[{"cat":"Blu-Ray","brand":"Insignia","model":"Insignia_NSWBRDVD2","url":"flipper_irdb/Blu-Ray/Insignia/Insignia_NSWBRDVD2.ir","path":"Blu-Ray/Insignia/Insignia_NSWBRDVD2.ir","buttons":["Power","Eject","Prev","Ok","Down","Up","Right","Left","Play","Pause","Stop","Fast_ba","Fast_fo"],"types":["parsed"]},{"cat":"Blu-Ray","brand":"JVC","model":"JVC_XVBP1","url":"flipper_irdb/Blu-Ray/JVC/JVC_XVBP1.ir","path":"Blu-Ray/JVC/JVC_XVBP1.ir","buttons":["Power","Eject","Prev","Ok","Up","Down","Left","Right","Fast_fo","Fast_ba","Pause","Play","Stop","Audio","Home","Subtitle"],"types":["parsed"]},{"cat":"Blu-Ray","brand":"LG","model":"LG_AKB73495301","url":"flipper_irdb/Blu-Ray/LG/LG_AKB73495301.ir","path":"Blu-Ray/LG/LG_AKB73495301.ir","buttons":["Power","1","2","3","4","5","6","7","8","9","0","Input","Tv_Power","Vol_up","Vol_dn","Ch_next","Ch_prev","Info","Mute","Up","Left","Down","Right","Enter","Back","R","G","Y","B","Stop","Play","Pause","Skip_Back","Skip_Fwd","Open/Close","Clear","Scan_Back","Scan_Fwd","Home","Disk_Menu","Zoom","Marker","Search","Title/Pop-Pup","Repeat","Audio","Subtitle"],"types":["parsed"]},{"cat":"Blu-Ray","brand":"LG","model":"LG_AKB73775801","url":"flipper_irdb/Blu-Ray/LG/LG_AKB73775801.ir","path":"Blu-Ray/LG/LG_AKB73775801.ir","buttons":["POWER","Home","Function","VOL+","VOL-","MUTE","Menu","Up","Down","Left","Right","Enter","Play","Pause","Stop","FF","Rew","Back","Next_Ch","Prev_Ch","Disc_Menu","Title","Optical","Open_Close","Speaker_Level","Sound_Effect","R","G","Y","B"],"types":["parsed"]},{"cat":"Blu-Ray","brand":"LG","model":"LG_BD650L","url":"flipper_irdb/Blu-Ray/LG/LG_BD650L.ir","path":"Blu-Ray/LG/LG_BD650L.ir","buttons":["Power","Input","Eject","Menu","Info","Ok","Up","Down","Left","Right","Fast_fo","Fast_ba","Pause","Play","Stop","Mute","Vol_up","Vol_dn","Home"],"types":["parsed"]},{"cat":"Blu-Ray","brand":"LG","model":"LG_BD690","url":"flipper_irdb/Blu-Ray/LG/LG_BD690.ir","path":"Blu-Ray/LG/LG_BD690.ir","buttons":["Power","Eject","Menu","Info","Exit","Ok","Up","Down","Left","Right","Fast_fo","Fast_ba","Pause","Play","Stop","Title"],"types":["parsed"]},{"cat":"Blu-Ray","brand":"LG","model":"LG_BH9520TW","url":"flipper_irdb/Blu-Ray/LG/LG_BH9520TW.ir","path":"Blu-Ray/LG/LG_BH9520TW.ir","buttons":["Power","Eject","Menu","Back","Ok","Up","Down","Left","Right","Fast_fo","Fast_ba","Pause","Play","Stop","Mute","Vol_up","Vol_dn","Subtitle","Audio","Home","Record"],"types":["parsed"]},{"cat":"Blu-Ray","brand":"LG","model":"LG_BlueRay","url":"flipper_irdb/Blu-Ray/LG/LG_BlueRay.ir","path":"Blu-Ray/LG/LG_BlueRay.ir","buttons":["POWER","Eject","Pause","Play","Stop","Forward","Backward","Chptr_next","Chpter_back","Title_popup","Info_menu","Home","Up","Down","Left","Right","Enter","Disc_menu"],"types":["parsed"]},{"cat":"Blu-Ray","brand":"LG","model":"LG_LHB655","url":"flipper_irdb/Blu-Ray/LG/LG_LHB655.ir","path":"Blu-Ray/LG/LG_LHB655.ir","buttons":["POWER","Input","Eject","Subtitle","Sleep","Info","Home","DiscMenu","Up","Down","Left","Right","Enter","Back","TitlePopup","Stop","Play","Pause","SkipBack","SkipForward","ScanBack","ScanForward","SpeakerLevel","SoundEffect","Optical_TVSound","MUTE","VolUp","VolDown","Red","Green","Yellow","Blue","1","2","3","4","5","6","7","8","9","0","Audio","Rec","Asterisk1","Asterisk2","Repeat","Clear"],"types":["parsed"]},{"cat":"Blu-Ray","brand":"LG","model":"LG_UBK80","url":"flipper_irdb/Blu-Ray/LG/LG_UBK80.ir","path":"Blu-Ray/LG/LG_UBK80.ir","buttons":["Power","Eject","Menu","Prev","Ok","Up","Down","Left","Right","Fast_fo","Fast_ba","Pause","Play","Stop","Home"],"types":["parsed"]},{"cat":"Blu-Ray","brand":"Marantz","model":"Marantz_BD8002","url":"flipper_irdb/Blu-Ray/Marantz/Marantz_BD8002.ir","path":"Blu-Ray/Marantz/Marantz_BD8002.ir","buttons":["Power","Setup","Eject","Menu","Exit","Ok","Up","Down","Left","Right","Fast_fo","Fast_ba","Pause","Play","Stop","Audio","Topmenu"],"types":["raw"]},{"cat":"Blu-Ray","brand":"Marantz","model":"Marantz_UD7007_(RC006UD)","url":"flipper_irdb/Blu-Ray/Marantz/Marantz_UD7007_(RC006UD).ir","path":"Blu-Ray/Marantz/Marantz_UD7007_(RC006UD).ir","buttons":["Power","Open/Close","Play","Pause","Stop","Menu","Next","Previous","FF","Rew","Audio Track","Subtitle","Angle","Option","Top Menu","Pop Up Menu","Return","Setup","Repeat","A-B","Random","Pure","Resolution","Page","Layer","Picture Adjust","RED","GREEN","YELLOW","BLUE","1","2","3","4","5","6","7","8","9","0","+10","Prog/Direct","Clear","Call","Search","Dimmer","Info","YouTube","Netflix","Vudu","Power_Amp","Vol_up","Vol_dn","Mute","Input_up","Input_dn"],"types":["raw"]},{"cat":"Blu-Ray","brand":"NAD","model":"NAD_T557","url":"flipper_irdb/Blu-Ray/NAD/NAD_T557.ir","path":"Blu-Ray/NAD/NAD_T557.ir","buttons":["Power","Eject","Menu","Prev","Ok","Up","Down","Left","Right","Fast_fo","Fast_ba","Pause","Play","Stop","Subtitle","Home","Audio","Popup"],"types":["parsed"]},{"cat":"Blu-Ray","brand":"Oppo","model":"OPPO_BDP103","url":"flipper_irdb/Blu-Ray/Oppo/OPPO_BDP103.ir","path":"Blu-Ray/Oppo/OPPO_BDP103.ir","buttons":["Power","Input","Eject","Menu","Info","Prev","Ok","Up","Down","Left","Right","Fast_fo","Fast_ba","Pause","Play","Stop","Mute","Vol_up","Vol_dn","Subtitle","Netflix","Audio","PopUp","Top_menu"],"types":["parsed"]},{"cat":"Blu-Ray","brand":"Oppo","model":"OPPO_BDP93","url":"flipper_irdb/Blu-Ray/Oppo/OPPO_BDP93.ir","path":"Blu-Ray/Oppo/OPPO_BDP93.ir","buttons":["POWER","VOL+","VOL-","MUTE","Open","Input","Up","Down","Left","Right","Enter","Play","Pause","Stop","Options","Return","1","2","3","4","5","6","7","8","9","0","Red","Green","Blue","Yellow","Home","PureAudio","Netflix","Vudu","PgUp","PgDwn","Info","Goto","TopMenu","PopUpMenu","Audio","Subtitle","Zoom","Dimmer","Setup","ABReplay","Repeat","Darbee","Resolution","Light","Clear"],"types":["parsed"]},{"cat":"Blu-Ray","brand":"Panasonic","model":"Panasonic_DMPBDT167","url":"flipper_irdb/Blu-Ray/Panasonic/Panasonic_DMPBDT167.ir","path":"Blu-Ray/Panasonic/Panasonic_DMPBDT167.ir","buttons":["Power","Eject","Prev","Ok","Up","Down","Left","Right","Fast_fo","Fast_ba","Pause","Play","Stop","Netflix","Audio","PopUp","Top_menu","Exit"],"types":["parsed"]},{"cat":"Blu-Ray","brand":"Panasonic","model":"Panasonic_DMP_BD75","url":"flipper_irdb/Blu-Ray/Panasonic/Panasonic_DMP_BD75.ir","path":"Blu-Ray/Panasonic/Panasonic_DMP_BD75.ir","buttons":["Power","TV_Power","TV_Vol+","TV_Vol-","TV_Input","Up","Down","Left","Right","Exit","Return","Option","OK","PopUpMenu","Home","TopMenu","Netflix","Play","Pause","Stop","Rewind","FastForward","Skip","Previous","1","2","3","4","5","6","7","8","9","0","Cancel","Audio","Open/Close","Status","Miracast","Internet","Red","Green","Yellow","Blue"],"types":["parsed"]},{"cat":"Blu-Ray","brand":"Panasonic","model":"Panasonic_DMRBWT720","url":"flipper_irdb/Blu-Ray/Panasonic/Panasonic_DMRBWT720.ir","path":"Blu-Ray/Panasonic/Panasonic_DMRBWT720.ir","buttons":["Power","Menu","Info","Back","Ok","Up","Down","Left","Right","Fast_fo","Fast_ba","Pause","Play","Stop","Ch_next","Ch_prev","Subtitle","PopUpMenu","PageUp","PageDown","Record"],"types":["parsed"]},{"cat":"Blu-Ray","brand":"Panasonic","model":"Panasonic_DPUB420","url":"flipper_irdb/Blu-Ray/Panasonic/Panasonic_DPUB420.ir","path":"Blu-Ray/Panasonic/Panasonic_DPUB420.ir","buttons":["Power","Eject","Prev","Ok","Up","Down","Left","Right","Fast_fo","Fast_ba","Pause","Play","Stop","Subtitle","Home","Netflix","Audio","Top_menu","PopUp","Exit"],"types":["parsed"]},{"cat":"Blu-Ray","brand":"Panasonic","model":"Panasonic_DPUB820","url":"flipper_irdb/Blu-Ray/Panasonic/Panasonic_DPUB820.ir","path":"Blu-Ray/Panasonic/Panasonic_DPUB820.ir","buttons":["Power","Eject","Prev","Ok","Up","Down","Left","Right","Fast_fo","Fast_ba","Pause","Play","Stop","Subtitle","Netflix","Audio","Top_menu","PopUp","Home"],"types":["parsed"]},{"cat":"Blu-Ray","brand":"Philips","model":"Philips_BDP2501F7","url":"flipper_irdb/Blu-Ray/Philips/Philips_BDP2501F7.ir","path":"Blu-Ray/Philips/Philips_BDP2501F7.ir","buttons":["Power","Eject","Menu","Prev","Ok","Up","Down","Left","Right","Fast_fo","Fast_ba","Pause","Play","Stop","Home","Netflix","YouTube"],"types":["parsed"]},{"cat":"Blu-Ray","brand":"Philips","model":"Philips_BDP2700","url":"flipper_irdb/Blu-Ray/Philips/Philips_BDP2700.ir","path":"Blu-Ray/Philips/Philips_BDP2700.ir","buttons":["Power","Eject","Menu","Prev","Ok","Up","Down","Left","Right","Fast_fo","Fast_ba","Pause","Play","Stop","Subtitle","Home","1","2","3","4","5","6","7","8","9","0"],"types":["parsed"]},{"cat":"Blu-Ray","brand":"Philips","model":"Philips_BDP7302","url":"flipper_irdb/Blu-Ray/Philips/Philips_BDP7302.ir","path":"Blu-Ray/Philips/Philips_BDP7302.ir","buttons":["Power","Eject","Menu","Info","Prev","Ok","Up","Down","Left","Right","Fast_fo","Fast_ba","Play_pa","Pause","Home","Subtitle","1","2","3","4","5","6","7","8","9","0"],"types":["parsed"]},{"cat":"Blu-Ray","brand":"Pioneer","model":"Pioneer_BDP150","url":"flipper_irdb/Blu-Ray/Pioneer/Pioneer_BDP150.ir","path":"Blu-Ray/Pioneer/Pioneer_BDP150.ir","buttons":["Power","Eject","Menu","Back","Ok","Up","Down","Right","Fast_fo","Fast_ba","Pause","Play","Stop","Left","Subtitle","Audio","PopUpMenu","Top_Menu"],"types":["parsed"]},{"cat":"Blu-Ray","brand":"Pioneer","model":"Pioneer_BDP320","url":"flipper_irdb/Blu-Ray/Pioneer/Pioneer_BDP320.ir","path":"Blu-Ray/Pioneer/Pioneer_BDP320.ir","buttons":["Power","Eject","Menu","Prev","Ok","Up","Down","Left","Right","Fast_fo","Fast_ba","Pause","Play","Stop","Audio","Popup","Top_menu","Subtitle"],"types":["parsed"]},{"cat":"Blu-Ray","brand":"Pioneer","model":"Pioneer_BDP43FD","url":"flipper_irdb/Blu-Ray/Pioneer/Pioneer_BDP43FD.ir","path":"Blu-Ray/Pioneer/Pioneer_BDP43FD.ir","buttons":["Power","Eject","Menu","Prev","Ok","Up","Down","Left","Right","Fast_fo","Fast_ba","Pause","Play","Stop","Subtitle","1","2","3","4","5","6","7","8","9","0"],"types":["parsed"]},{"cat":"Blu-Ray","brand":"Samsung","model":"Samsung_AK59_00149A","url":"flipper_irdb/Blu-Ray/Samsung/Samsung_AK59_00149A.ir","path":"Blu-Ray/Samsung/Samsung_AK59_00149A.ir","buttons":["POWER","Disk","Up","Down","Left","Right","Ok","Return","Play","Pause","Vol+","Vol-","Source","Forward","Backward","Home","Subtitle","Tools"],"types":["parsed","raw"]},{"cat":"Blu-Ray","brand":"Samsung","model":"Samsung_B59-01301A","url":"flipper_irdb/Blu-Ray/Samsung/Samsung_B59-01301A.ir","path":"Blu-Ray/Samsung/Samsung_B59-01301A.ir","buttons":["Power","Source","Vol+","Vol-","Ch+","Ch-","1","2","3","4","5","6","7","8","9","0","-","Pre_CH","Mute","CH_List","Home","Sleep","Guide","Settings","Info","Up","Left","Right","Down","Enter","Return","Exit","A","B","C","D","E_Manual","P_Size","CC_VD","Reverse","Play","Pause","Fast_Forward"],"types":["parsed"]},{"cat":"Blu-Ray","brand":"Samsung","model":"Samsung_BD-D5300","url":"flipper_irdb/Blu-Ray/Samsung/Samsung_BD-D5300.ir","path":"Blu-Ray/Samsung/Samsung_BD-D5300.ir","buttons":["Power","Disc Menu","Popup/Title Menu","Red","Green","Yellow","Blue","1","2","3","4","5","6","7","8","9","Subtitle","0","Audio","Previous","Info","Pause","Next","Rewind","Stop","Play","Fast Forward","Menu","Up","Tools","Left","Ok","Right","Return","Down","Exit","Smart Hub","Search"],"types":["raw"]},{"cat":"Blu-Ray","brand":"Samsung","model":"Samsung_BDD7500","url":"flipper_irdb/Blu-Ray/Samsung/Samsung_BDD7500.ir","path":"Blu-Ray/Samsung/Samsung_BDD7500.ir","buttons":["Power","Eject","Menu","Info","Prev","Ok","Up","Down","Left","Right","Fast_fo","Fast_ba","Pause","Play","Stop","Subtitle","Netflix","Audio","Popup"],"types":["raw"]},{"cat":"Blu-Ray","brand":"Samsung","model":"Samsung_BDE5300","url":"flipper_irdb/Blu-Ray/Samsung/Samsung_BDE5300.ir","path":"Blu-Ray/Samsung/Samsung_BDE5300.ir","buttons":["Power","Eject","Menu","Info","Back","Ok","Up","Down","Left","Right","Fast_fo","Fast_ba","Pause","Play","Stop","Subtitle","PopUp","Netflix","Exit","Audio"],"types":["raw"]},{"cat":"Blu-Ray","brand":"Samsung","model":"Samsung_UBDK8500","url":"flipper_irdb/Blu-Ray/Samsung/Samsung_UBDK8500.ir","path":"Blu-Ray/Samsung/Samsung_UBDK8500.ir","buttons":["Power","Eject","Menu","Info","Prev","Ok","Up","Down","Left","Right","Fast_fo","Fast_ba","Pause","Play","Stop","Home"],"types":["raw"]},{"cat":"Blu-Ray","brand":"Sanyo","model":"Sanyo_Bluray_NC088","url":"flipper_irdb/Blu-Ray/Sanyo/Sanyo_Bluray_NC088.ir","path":"Blu-Ray/Sanyo/Sanyo_Bluray_NC088.ir","buttons":["Power","Eject","Home","Disc_menu","Mode","Up","Left","Right","Down","Ok","Search","Return","Rew","Fwd","Play","Prev","Next","Stop","Pause","Display","Repeat","Subtitle","Audio","R","G","B","Y"],"types":["parsed"]},{"cat":"Blu-Ray","brand":"Sharp","model":"Sharp_BDHP20","url":"flipper_irdb/Blu-Ray/Sharp/Sharp_BDHP20.ir","path":"Blu-Ray/Sharp/Sharp_BDHP20.ir","buttons":["Power","Eject","Menu","List","Ok","Up","Down","Left","Right","Fast_fo","Fast_ba","Pause","Play","Stop","Subtitle"],"types":["raw"]},{"cat":"Blu-Ray","brand":"Sharp","model":"Sharp_BDHP70U","url":"flipper_irdb/Blu-Ray/Sharp/Sharp_BDHP70U.ir","path":"Blu-Ray/Sharp/Sharp_BDHP70U.ir","buttons":["Power","Eject","Prev","Ok","Up","Down","Left","Right","Pause","Play","Fast_ba","Fast_fo","Exit","Menu","Stop"],"types":["raw"]},{"cat":"Blu-Ray","brand":"Soniq","model":"Soniq_B100","url":"flipper_irdb/Blu-Ray/Soniq/Soniq_B100.ir","path":"Blu-Ray/Soniq/Soniq_B100.ir","buttons":["Power","Eject","Menu","Info","Prev","Ok","Up","Down","Left","Right","Fast_fo","Fast_ba","Pause","Play","Stop","Mute","Vol_up","Vol_dn","Audio","Subtitle"],"types":["parsed"]},{"cat":"Blu-Ray","brand":"Sony","model":"RMT_VB201U","url":"flipper_irdb/Blu-Ray/Sony/RMT_VB201U.ir","path":"Blu-Ray/Sony/RMT_VB201U.ir","buttons":["POWER","TV_POWER","TV_Input","Up","Down","Left","Right","Enter","Return","Play","Pause","FastForward","Rewind","Next","Prev","Stop","Open_Close","Top_Menu","Popup_Menu","Subtitles","Options","Audio","Yellow","Blue","Red","Green","Home","Favorite","Netflix","Muting","Display","TV_Vol_Up","TV_Vol_Dn"],"types":["parsed"]},{"cat":"Blu-Ray","brand":"Sony","model":"Sony_BDP-N460_Blu-Ray","url":"flipper_irdb/Blu-Ray/Sony/Sony_BDP-N460_Blu-Ray.ir","path":"Blu-Ray/Sony/Sony_BDP-N460_Blu-Ray.ir","buttons":["POWER","Up","Down","Left","Right","Home","Play","Pause","Stop","Rewind","Fastforward","Previous","Next","Enter","Display","Top_Menu","Popup_Menu","Return","Options","Vol+","Vol-","Audio","Subtitle","Angle","Time","Display","Theater","Input","Red","Green","Blue","Yellow","1","2","3","4","5","6","7","8","9","0"],"types":["parsed"]},{"cat":"Blu-Ray","brand":"Sony","model":"Sony_BDP-S370","url":"flipper_irdb/Blu-Ray/Sony/Sony_BDP-S370.ir","path":"Blu-Ray/Sony/Sony_BDP-S370.ir","buttons":["Open/Close","TV Input","TV Power","Power","1","2","3","Vol_up","4","5","6","Vol_dn","7","8","9","Theater","Audio","0","Subtitle","Favorites","Yellow","Blue","Red","Green","Top Menu","Up","Pop Up/Menu","Left","Ok","Right","Return","Down","Options","Home","Previous","Replay","Advance","Next","Rewind","Play","Fast Forward","Display","Pause","Stop"],"types":["parsed"]},{"cat":"Blu-Ray","brand":"Sony","model":"Sony_BDP-S5200","url":"flipper_irdb/Blu-Ray/Sony/Sony_BDP-S5200.ir","path":"Blu-Ray/Sony/Sony_BDP-S5200.ir","buttons":["Open/Close","TV Input","TV Power","Power","Yellow","Blue","Red","Green","Top Menu","Up","Pop Up/Menu","Left","Ok","Right","Return","Down","Options","Home","Sen","Netflix","Rewind","Play","Fast Forward","Previous","Pause","Stop","Next","Subtitle","Vol_up","Audio","Muting","Vol_dn","Display"],"types":["parsed"]},{"cat":"Blu-Ray","brand":"Sony","model":"Sony_BDPBX120","url":"flipper_irdb/Blu-Ray/Sony/Sony_BDPBX120.ir","path":"Blu-Ray/Sony/Sony_BDPBX120.ir","buttons":["Power","Eject","Menu","Back","Ok","Up","Down","Left","Right","Fast_fo","Fast_ba","Pause","Play","Stop","Subtitle","Netflix","Topmenu","Audio"],"types":["parsed"]},{"cat":"Blu-Ray","brand":"Sony","model":"Sony_BDPS1700","url":"flipper_irdb/Blu-Ray/Sony/Sony_BDPS1700.ir","path":"Blu-Ray/Sony/Sony_BDPS1700.ir","buttons":["Power","Eject","Menu","Prev","Ok","Up","Down","Left","Right","Fast_fo","Fast_ba","Pause","Play","Stop","Mute","Vol_up","Vol_dn","Subtitle","Netflix","Audio","Top_menu"],"types":["parsed"]},{"cat":"Blu-Ray","brand":"Sony","model":"Sony_BDPS360","url":"flipper_irdb/Blu-Ray/Sony/Sony_BDPS360.ir","path":"Blu-Ray/Sony/Sony_BDPS360.ir","buttons":["Power","Eject","Menu","Prev","Ok","Up","Down","Left","Right","Fast_fo","Fast_ba","Pause","Play","Stop","Subtitle","Audio","PopUp","Top_menu"],"types":["parsed"]},{"cat":"Blu-Ray","brand":"Sony","model":"Sony_BDPS770","url":"flipper_irdb/Blu-Ray/Sony/Sony_BDPS770.ir","path":"Blu-Ray/Sony/Sony_BDPS770.ir","buttons":["Power","Eject","Menu","Prev","Ok","Up","Down","Left","Right","Fast_fo","Fast_ba","Pause","Play","Stop","Subtitle","Audio","PopUp","Top_menu","Home"],"types":["parsed"]},{"cat":"Blu-Ray","brand":"Sony","model":"Sony_BD_RMT_B110A","url":"flipper_irdb/Blu-Ray/Sony/Sony_BD_RMT_B110A.ir","path":"Blu-Ray/Sony/Sony_BD_RMT_B110A.ir","buttons":["Power","Tv On","Imput","Close CD","Vol Up","Vol Down","Mute","Subtitle","Audio","1","2","3","4","5","6","7","8","9","0","Yellow","Blue","Red","Green","Top menu","Pop Up Menu","Return","Return","Options","Up","Down","Right","Left","Center","Home","Pause","Play","Next","Prev","Fastforward","Rewind","Stop","Display","Favorites"],"types":["parsed"]},{"cat":"Blu-Ray","brand":"Sony","model":"Sony_BR_RMT_B120P","url":"flipper_irdb/Blu-Ray/Sony/Sony_BR_RMT_B120P.ir","path":"Blu-Ray/Sony/Sony_BR_RMT_B120P.ir","buttons":["Open_Close","TV_Input","TV_Power","Power","1","2","3","4","5","6","7","8","9","Audio","0","Subtitle","Favorite","Red","Green","Yellow","Blue","Up","Down","Left","Right","Enter","Top_Menu","Popup_Menu","Return","Options","Home","Rewind","Pause","FastForward","Prev","Play","Next","Display","Stop","Sen"],"types":["parsed"]},{"cat":"Blu-Ray","brand":"Sony","model":"Sony_RMT_VB100I","url":"flipper_irdb/Blu-Ray/Sony/Sony_RMT_VB100I.ir","path":"Blu-Ray/Sony/Sony_RMT_VB100I.ir","buttons":["Power","Open_Close","Tv_input","tv_power","Red","Green","Yellow","Blue","Up","Down","Left","Right","Enter","Top_menu","Pop_up_menu","Return","Options","Home","Favorite","Netflix","Play","Pause","Stop","Fast_forward","Rewind","Prev","Next","Vol_up","Vol_dn","Mute","Substile","Audio","Display"],"types":["parsed"]},{"cat":"Blu-Ray","brand":"Sony","model":"Sony_RMT_VB100U","url":"flipper_irdb/Blu-Ray/Sony/Sony_RMT_VB100U.ir","path":"Blu-Ray/Sony/Sony_RMT_VB100U.ir","buttons":["Power","Setup","Eject","Menu","List","Info","Back","Ok","Up","Down","Left","Right","Next","Prev","Fast_fo","Fast_ba","Play_pa","Pause","Play","Stop","Vol_up","Vol_dn","Home","Subtitle","Audio"],"types":["parsed","raw"]},{"cat":"Blu-Ray","brand":"Sony","model":"Sony_RMT_VB310E","url":"flipper_irdb/Blu-Ray/Sony/Sony_RMT_VB310E.ir","path":"Blu-Ray/Sony/Sony_RMT_VB310E.ir","buttons":["Power","Tv_power","Open_close","Net_service","Tv_input","Bluetooth","Red","Green","Yellow","Blue","Favorite","Netflix","Top_menu","Pop_up_menu","Up","Down","Left","Right","Enter","Return","Options","Home","Play","Pause","Stop","Rewind","Fast_forward","Prev","Next","Substile","Audio","Mute","Vol_up_tv","Vol_dn_tv","Display"],"types":["parsed"]},{"cat":"Blu-Ray","brand":"Sony","model":"Sony_UBPX700","url":"flipper_irdb/Blu-Ray/Sony/Sony_UBPX700.ir","path":"Blu-Ray/Sony/Sony_UBPX700.ir","buttons":["Power","Eject","Prev","Ok","Up","Down","Left","Right","Fast_fo","Fast_ba","Pause","Play","Stop","Mute","Subtitle","Home","Netflix","Audio","Top_menu","PopUp"],"types":["parsed"]},{"cat":"Blu-Ray","brand":"Sylvania","model":"Sylvania_SDVD1111","url":"flipper_irdb/Blu-Ray/Sylvania/Sylvania_SDVD1111.ir","path":"Blu-Ray/Sylvania/Sylvania_SDVD1111.ir","buttons":["Power","Eject","Menu","Info","Ok","Up","Down","Left","Right","Fast_fo","Fast_ba","Pause","Play","Stop","Mute","Subtitle","Audio","Popup"],"types":["parsed","raw"]},{"cat":"Blu-Ray","brand":"Toshiba","model":"Toshiba_SE-R0398","url":"flipper_irdb/Blu-Ray/Toshiba/Toshiba_SE-R0398.ir","path":"Blu-Ray/Toshiba/Toshiba_SE-R0398.ir","buttons":["POWER","Setup","Eject","OK","Up","Down","Left","Right","Return","Menu","Display","Topmenu","Play","Stop","Back","Forward","Rewind","FF","MC","Audio","Subtitle","PIPAudio","Angle","Clear","Search","Repeat","AB","HDMI","OSC","PIP","Program","Digest","Zoom","Bookmark","1","2","3","4","5","6","7","8","9","0","Next"],"types":["parsed"]},{"cat":"Blu-Ray","brand":"Vizio","model":"Vizio_VBR220","url":"flipper_irdb/Blu-Ray/Vizio/Vizio_VBR220.ir","path":"Blu-Ray/Vizio/Vizio_VBR220.ir","buttons":["Power","Eject","Menu","Info","Prev","Ok","Up","Down","Left","Right","Fast_fo","Fast_ba","Pause","Play","Stop","Subtitle","1","2","3","4","5","6","7","8","9","0"],"types":["parsed","raw"]},{"cat":"Blu-Ray","brand":"Vizio","model":"Vizio_VBR333","url":"flipper_irdb/Blu-Ray/Vizio/Vizio_VBR333.ir","path":"Blu-Ray/Vizio/Vizio_VBR333.ir","buttons":["Power","Eject","Info","Prev","Ok","Up","Down","Left","Right","Fast_fo","Fast_ba","Pause","Play","Stop","Subtitle","Audio","PopUp","TitleMenu","Cancel"],"types":["parsed"]},{"cat":"Blu-Ray","brand":"Yamaha","model":"Yamaha_BDS667","url":"flipper_irdb/Blu-Ray/Yamaha/Yamaha_BDS667.ir","path":"Blu-Ray/Yamaha/Yamaha_BDS667.ir","buttons":["Power","Setup","Eject","Menu","Prev","Ok","Up","Down","Left","Right","Fast_fo","Fast_ba","Pause","Play","Stop","Audio","Top_menu"],"types":["parsed"]}]