[{"cat":"Monitors","brand":"Aorus","model":"Aorus_FV43U","url":"flipper_irdb/Monitors/Aorus/Aorus_FV43U.ir","path":"Monitors/Aorus/Aorus_FV43U.ir","buttons":["Power","Source","Mute","Vol_up","Vol_dn","Select","Up","Down","Right","Left","Pic_Mode","Space_au"],"types":["parsed"]},{"cat":"Monitors","brand":"BenQ","model":"BenQ_EX2780Q","url":"flipper_irdb/Monitors/BenQ/BenQ_EX2780Q.ir","path":"Monitors/BenQ/BenQ_EX2780Q.ir","buttons":["Power","Input","Up","Right","Down","Left","Ok","HDRi","Menu","Bi","Low Blue Light","Audio Scenario","Mute","VOL-","VOL+"],"types":["parsed"]},{"cat":"Monitors","brand":"Clinton_Electronics","model":"Clinton_Electronics_M-10A","url":"flipper_irdb/Monitors/Clinton_Electronics/Clinton_Electronics_M-10A.ir","path":"Monitors/Clinton_Electronics/Clinton_Electronics_M-10A.ir","buttons":["Power","Source","Menu","Exit","Enter","Up","Down","Right","Left","Mute","Swap","Pip","Auto","Vol_Up","Vol_Dwn"],"types":["parsed"]},{"cat":"Monitors","brand":"LG","model":"LG_43UD79-B","url":"flipper_irdb/Monitors/LG/LG_43UD79-B.ir","path":"Monitors/LG/LG_43UD79-B.ir","buttons":["Power","Vol_up","Vol_dn","Mute","Bright_up","Bright_dn","OK","Up","Down","Left","Right","Menu","Exit","Game_mode","Picture_mode","PBP_pip","Full_screen","Audio Select"],"types":["parsed"]},{"cat":"Monitors","brand":"LG","model":"LG_UltraGear_OLED_Monitor","url":"flipper_irdb/Monitors/LG/LG_UltraGear_OLED_Monitor.ir","path":"Monitors/LG/LG_UltraGear_OLED_Monitor.ir","buttons":["Power","Input","Brightness Up","Brightness Dwn","Mute","Settings","Vol_up","Vol_dwn","Reader Mode","Previous","Up","Down","Right","Left","Enter","DTS","Sound Out","OLED Care","User Specified 1","User Specified 2"],"types":["parsed"]},{"cat":"Monitors","brand":"Loncevon","model":"LONCEVON-12_inch_Small_Monitor","url":"flipper_irdb/Monitors/Loncevon/LONCEVON-12_inch_Small_Monitor.ir","path":"Monitors/Loncevon/LONCEVON-12_inch_Small_Monitor.ir","buttons":["On/Off","Source","USB/SD","UP","Down","Right","Left","Mute","Exit","Pause/Play","Menu","Volume_Down","Volume_Up","Rewind","Fastforward","Skip_forward","Skip_backwards"],"types":["parsed"]},{"cat":"Monitors","brand":"Monoprice","model":"Monoprice_43305","url":"flipper_irdb/Monitors/Monoprice/Monoprice_43305.ir","path":"Monitors/Monoprice/Monoprice_43305.ir","buttons":["Power","Input_Select","Menu_OK","Up","Down","Right","Left","Exit_Menu","Vol_up","Vol_dn","Cross_Hairs","Aspect_Ratio","Bright_up","Bright_dn","HDR","Multi_Window"],"types":["parsed"]},{"cat":"Monitors","brand":"Philips","model":"Philips_Evnia_49M2C8900L","url":"flipper_irdb/Monitors/Philips/Philips_Evnia_49M2C8900L.ir","path":"Monitors/Philips/Philips_Evnia_49M2C8900L.ir","buttons":["Power","Source","Ok","Up","Down","Left","Right","Menu","SmartImage","Back","Vol_up","Vol_dn","Unmute","Mute","Brightness_up","Brightness_dn"],"types":["parsed"]}]